Lab3/bram11.v
// bram behavior code (can't be synthesis)
// 11 words
module bram11 
(
    CLK,
    WE,
    EN,
    Di,
    Do,
    A
);

    input   wire            CLK;
    input   wire    [3:0]   WE;
    input   wire            EN;
    input   wire    [31:0]  Di;
    output  reg     [31:0]  Do;
    input   wire    [11:0]   A; 

    //  11 words
	reg [31:0] RAM[0:10];
    reg [11:0] r_A;

    always @(posedge CLK) begin
        r_A <= A;
    end

    // assign Do = {32{EN}} & RAM[r_A>>2];    // read
    always@* begin
        Do = {32{EN}} & RAM[r_A>>2];
    end
    reg [31:0] Temp_D;
    always @(posedge CLK) begin
        if(EN) begin
	    if(WE[0]) RAM[A>>2][7:0] <= Di[7:0];
            if(WE[1]) RAM[A>>2][15:8] <= Di[15:8];
            if(WE[2]) RAM[A>>2][23:16] <= Di[23:16];
            if(WE[3]) RAM[A>>2][31:24] <= Di[31:24];
        end
    end

endmodule

Lab3/fir.v
module fir 
#(  parameter pADDR_WIDTH = 12,
    parameter pDATA_WIDTH = 32,
    parameter Tape_Num    = 11
)
(
    output  wire                     awready,
    output  wire                     wready,
    input   wire                     awvalid,
    input   wire [(pADDR_WIDTH-1):0] awaddr,
    input   wire                     wvalid,
    input   wire [(pDATA_WIDTH-1):0] wdata,
    output  wire                     arready,
    input   wire                     rready,
    input   wire                     arvalid,
    input   wire [(pADDR_WIDTH-1):0] araddr,
    output  wire                     rvalid,
    output  wire [(pDATA_WIDTH-1):0] rdata,    
    input   wire                     ss_tvalid, 
    input   wire [(pDATA_WIDTH-1):0] ss_tdata, 
    input   wire                     ss_tlast, 
    output  wire                     ss_tready, 
    input   wire                     sm_tready, 
    output  wire                     sm_tvalid, 
    output  wire [(pDATA_WIDTH-1):0] sm_tdata, 
    output  wire                     sm_tlast, 
    
    // bram for tap RAM
    output  wire [3:0]               tap_WE,
    output  wire                     tap_EN,
    output  wire [(pDATA_WIDTH-1):0] tap_Di,
    output  wire [(pADDR_WIDTH-1):0] tap_A,
    input   wire [(pDATA_WIDTH-1):0] tap_Do,

    // bram for data RAM
    output  wire [3:0]               data_WE,
    output  wire                     data_EN,
    output  wire [(pDATA_WIDTH-1):0] data_Di,
    output  wire [(pADDR_WIDTH-1):0] data_A,
    input   wire [(pDATA_WIDTH-1):0] data_Do,

    input   wire                     axis_clk,
    input   wire                     axis_rst_n
);

reg r_awready, r_wready, r_arready, r_rvalid, r_ss_tready, r_sm_tvalid, r_sm_tlast;
reg [(pDATA_WIDTH-1):0] r_rdata, r_sm_tdata;
reg out_awready, out_wready, out_arready, out_rvalid, out_ss_tready, out_sm_tvalid, out_sm_tlast;
reg [(pDATA_WIDTH-1):0] out_rdata, out_sm_tdata;
reg m_tap_EN, m_data_EN;
reg [3:0] m_tap_WE, m_data_WE;
reg [(pDATA_WIDTH-1):0] m_tap_Di, m_data_Di;
reg [(pADDR_WIDTH-1):0] m_tap_A, m_data_A;


reg ap_start, n_ap_start, ap_done, n_ap_done, ap_idle, n_ap_idle;
reg out_rvalid_pre, out_rvalid_reg, last_flag, n_last_flag;
reg [10:0] data_num, n_data_num;
reg [(pDATA_WIDTH-1):0] y, pre_y, n_y;
reg [3:0] count_a, count_x, count, addr_flag, n_addr_flag;
reg [4:0] sum;
reg [1:0] state, n_state;
localparam IDLE = 2'd0, COEF = 2'd1, FIRR = 2'd2, IDLE2 = 2'd3;

// output
assign awready = r_awready;
assign wready = r_wready;
assign arready = r_arready;
assign rvalid = r_rvalid;
assign ss_tready = r_ss_tready;
assign sm_tvalid = r_sm_tvalid;
assign sm_tlast = r_sm_tlast;
assign rdata = r_rdata;
assign sm_tdata = r_sm_tdata;
assign tap_A = m_tap_A;
assign tap_Di = m_tap_Di;
assign tap_EN = m_tap_EN;
assign tap_WE = m_tap_WE;
assign data_A = m_data_A;
assign data_Di = m_data_Di;
assign data_EN = m_data_EN;
assign data_WE = m_data_WE;

// registers
always@(posedge axis_clk) begin
    if(~axis_rst_n) begin
        state <= IDLE;
        ap_start <= 1'b0;
        ap_done <= 1'b0;
        ap_idle <= 1'b1;
        data_num <= 10'b0;
        r_awready <= 1'b0;
        r_wready <= 1'b0;
        r_arready <= 1'b0;
        r_rvalid <= 1'b0;
        r_ss_tready <= 1'b0;
        r_sm_tvalid <= 1'b0;
        r_sm_tlast <= 1'b0;
        r_rdata <= 32'b0;
        r_sm_tdata <= 32'b0;
        out_rvalid_reg <= 1'b0;
        last_flag <= 1'b0;
        pre_y <= 32'b0;
        count_a <= 4'b0;
        count_x <= 4'b0;
        addr_flag <= 4'd1;
    end
    else begin
        state <= n_state;
        ap_start <= n_ap_start;
        ap_done <= n_ap_done;
        ap_idle <= n_ap_idle;
        data_num <= n_data_num;
        r_awready <= out_awready;
        r_wready <= out_wready;
        r_arready <= out_arready;
        r_rvalid <= out_rvalid;
        r_ss_tready <= out_ss_tready;
        r_sm_tvalid <= out_sm_tvalid;
        r_sm_tlast <= out_sm_tlast;
        r_rdata <= out_rdata;
        r_sm_tdata <= out_sm_tdata;
        out_rvalid_reg <= out_rvalid_pre;
        last_flag <= n_last_flag;
        pre_y <= n_y;
        count_a <= count;
        count_x <= count_a;
        addr_flag <= n_addr_flag;
    end
end

// read address
always@* begin
    if(r_rvalid) begin
        out_rvalid = 1'b0;
        out_rdata = 32'b0;
    end
    else if(state == COEF & araddr[7] & arvalid) begin
        out_rdata = tap_Do;
        out_rvalid = out_rvalid_reg;
    end
    else if (~araddr[7] & ~araddr[4] & arvalid) begin
        out_rdata = {29'b0, ap_idle, ap_done, ap_start};
        out_rvalid = 1'b1;
    end
    else begin
        out_rdata = 32'b0;
        out_rvalid = 1'b0;
    end 

    if(state == COEF & araddr[7] & arvalid) begin
        out_rvalid_pre = 1'b1;
    end
    else begin
        out_rvalid_pre = 1'b0;
    end
end

// ap_start
always@* begin
    if(~ap_idle) begin
        n_ap_start = 0;
    end
    else if(~awaddr[7] & ~awaddr[4] & awvalid & wvalid) begin
        n_ap_start = wdata[0];
    end
    else begin
        n_ap_start = ap_start;
    end
end

// ap_idle
always@* begin
    if(n_ap_start) begin
        n_ap_idle = 0;
    end
    else if(state == IDLE2 & ap_done & r_rvalid) begin
        n_ap_idle = 1;
    end
    else begin
        n_ap_idle = ap_idle;
    end
end

// ap_done
always@* begin
    if(out_sm_tlast) begin
        n_ap_done = 1'b1;
    end
    else if(ap_idle) begin
        n_ap_done = 1'b0;
    end
    else begin
        n_ap_done = ap_done;
    end
end

// FSM
always@* begin
    case(state)
    IDLE: begin
        n_state = COEF;
    end
    COEF: begin
        if(ap_start == 1) begin
            n_state = FIRR;
        end
        else begin
            n_state = COEF;
        end
    end
    FIRR: begin
        if(ap_done == 1) begin
            n_state = IDLE2;
        end
        else begin
            n_state = FIRR;
        end
    end
    IDLE2: begin
        if(ap_start == 1) begin
            n_state = FIRR;
        end
        else begin
            n_state = IDLE2;
        end
    end
    default: begin
        n_state = IDLE;
    end
    endcase
end

// data_num
always@* begin
    if(~awaddr[7] & awaddr[4] & awvalid & wvalid) begin
        n_data_num = wdata[11:0];
    end
    else begin
        n_data_num = data_num;
    end
end

// coef address
always@* begin
    if(state == COEF & awvalid & awaddr[7]) begin
        m_tap_A = {5'b0, awaddr[6:0]};
        m_tap_EN = r_wready;
        m_tap_WE = {4{r_wready}};
        m_tap_Di = wdata;
    end
    else if(state == COEF & arvalid & araddr[7]) begin
        m_tap_A = {5'b0, araddr[6:0]};
        m_tap_EN = out_rvalid;
        m_tap_WE = 4'b0;
        m_tap_Di = 32'b0;
    end
    else if(state == FIRR) begin
        m_tap_A = {6'b0, count_a, 2'b0};
        m_tap_EN = 1'b1;
        m_tap_WE = 4'b0;
        m_tap_Di = 32'b0;
    end
    else begin
        m_tap_A = 12'b0;
        m_tap_EN = 1'b0;
        m_tap_WE = 4'b0;
        m_tap_Di = 32'b0;
    end
end

// address flag
always@* begin
    if((count_a == 4'd10) & (addr_flag == 4'd10)) begin
        n_addr_flag = 4'd0;
    end
    else if(count_a == 4'd10) begin
        n_addr_flag = addr_flag + 1'b1;
    end
    else begin
        n_addr_flag = addr_flag;
    end
end

// data addr
always@* begin
    sum = count_a + addr_flag;
    m_data_WE = (state == COEF) ? m_tap_WE : (count_a == 4'd10) ? {4{1'b1}} : 4'b0;
    m_data_A  = (state == COEF) ? m_tap_A  : (sum <= 5'd10) ? {5'b0, sum, 2'b0} : {5'b0, (sum - 5'd11), 2'b0};
    m_data_Di = (state == COEF) ? 32'b0    : ss_tdata;
    m_data_EN = (state == FIRR) | m_tap_WE[0];
end

// control
always@* begin
    n_last_flag = (ss_tlast == 1'b1) ? 1'b1 : ((out_sm_tlast == 1'b1) ? 1'b0 : last_flag) ;
    out_ss_tready = (count == 4'd10);
    out_sm_tdata = y;
    out_sm_tvalid = (count_x == 4'd10);
    out_sm_tlast = ((last_flag == 1'b1) & (count_x == 4'd10));
    out_arready = 1;//out_rvalid;
    out_awready = 1;//awvalid; //(r_awready == 1'b1) ? 1'b0 : awvalid;
    out_wready = 1;//out_awready;
end 

// counter
always@* begin
    if ((count_a == 4'd10) | (state != FIRR)) begin
        count = 0;
    end
    else begin
        count = count_a + 1'b1;
    end
end

// FIR
always@* begin
    y = (tap_Do * data_Do) + pre_y;
    if (state != FIRR | (count_a == 4'd0)) begin
        n_y = 32'd0;
    end
    else begin
        n_y = y;
    end
end

endmodule

Lab3/fir_tb.v
`timescale 1ns / 1ps
//////////////////////////////////////////////////////////////////////////////////
// Company: 
// Engineer: 
// 
// Create Date: 08/20/2023 10:38:55 AM
// Design Name: 
// Module Name: fir_tb
// Project Name: 
// Target Devices: 
// Tool Versions: 
// Description: 
// 
// Dependencies: 
// 
// Revision:
// Revision 0.01 - File Created
// Additional Comments:
// 
//////////////////////////////////////////////////////////////////////////////////

`include "../bram/bram11.v"

module fir_tb
#(  parameter pADDR_WIDTH = 12,
    parameter pDATA_WIDTH = 32,
    parameter Tape_Num    = 11,
    parameter Data_Num    = 600
)();
    wire                        awready;
    wire                        wready;
    reg                         awvalid;
    reg   [(pADDR_WIDTH-1): 0]  awaddr;
    reg                         wvalid;
    reg signed [(pDATA_WIDTH-1) : 0] wdata;
    wire                        arready;
    reg                         rready;
    reg                         arvalid;
    reg         [(pADDR_WIDTH-1): 0] araddr;
    wire                        rvalid;
    wire signed [(pDATA_WIDTH-1): 0] rdata;
    reg                         ss_tvalid;
    reg signed [(pDATA_WIDTH-1) : 0] ss_tdata;
    reg                         ss_tlast;
    wire                        ss_tready;
    reg                         sm_tready;
    wire                        sm_tvalid;
    wire signed [(pDATA_WIDTH-1) : 0] sm_tdata;
    wire                        sm_tlast;
    reg                         axis_clk;
    reg                         axis_rst_n;

// ram for tap
    wire [3:0]               tap_WE;
    wire                     tap_EN;
    wire [(pDATA_WIDTH-1):0] tap_Di;
    wire [(pADDR_WIDTH-1):0] tap_A;
    wire [(pDATA_WIDTH-1):0] tap_Do;

// ram for data RAM
    wire [3:0]               data_WE;
    wire                     data_EN;
    wire [(pDATA_WIDTH-1):0] data_Di;
    wire [(pADDR_WIDTH-1):0] data_A;
    wire [(pDATA_WIDTH-1):0] data_Do;



    fir fir_DUT(
        .awready(awready),
        .wready(wready),
        .awvalid(awvalid),
        .awaddr(awaddr),
        .wvalid(wvalid),
        .wdata(wdata),
        .arready(arready),
        .rready(rready),
        .arvalid(arvalid),
        .araddr(araddr),
        .rvalid(rvalid),
        .rdata(rdata),
        .ss_tvalid(ss_tvalid),
        .ss_tdata(ss_tdata),
        .ss_tlast(ss_tlast),
        .ss_tready(ss_tready),
        .sm_tready(sm_tready),
        .sm_tvalid(sm_tvalid),
        .sm_tdata(sm_tdata),
        .sm_tlast(sm_tlast),

        // ram for tap
        .tap_WE(tap_WE),
        .tap_EN(tap_EN),
        .tap_Di(tap_Di),
        .tap_A(tap_A),
        .tap_Do(tap_Do),

        // ram for data
        .data_WE(data_WE),
        .data_EN(data_EN),
        .data_Di(data_Di),
        .data_A(data_A),
        .data_Do(data_Do),

        .axis_clk(axis_clk),
        .axis_rst_n(axis_rst_n)

        );
    
    // RAM for tap
    bram11 tap_RAM (
        .CLK(axis_clk),
        .WE(tap_WE),
        .EN(tap_EN),
        .Di(tap_Di),
        .A(tap_A),
        .Do(tap_Do)
    );

    // RAM for data: choose bram11 or bram12
    bram11 data_RAM(
        .CLK(axis_clk),
        .WE(data_WE),
        .EN(data_EN),
        .Di(data_Di),
        .A(data_A),
        .Do(data_Do)
    );

    reg signed [(pDATA_WIDTH-1):0] Din_list[0:(Data_Num-1)];
    reg signed [(pDATA_WIDTH-1):0] golden_list[0:(Data_Num-1)];

    initial begin
        $dumpfile("fir.vcd");
        $dumpvars();
    end


    initial begin
        axis_clk = 0;
        forever begin
            #5 axis_clk = (~axis_clk);
        end
    end

    initial begin
        axis_rst_n = 0;
        @(posedge axis_clk); @(posedge axis_clk);
        axis_rst_n = 1;
    end

    integer clk_start, clk_done, clk_accu;
    initial begin
        clk_start = 0;
        clk_done = 0;
        clk_accu = 0;
        wait (clk_start);
        while (clk_done != 1) begin
            @(posedge axis_clk) clk_accu = clk_accu + 1;
        end
    end

    reg [31:0]  data_length;
    integer Din, golden, input_data, golden_data, m;
    initial begin
        data_length = 0;
        Din = $fopen("./samples_triangular_wave.dat","r");
        golden = $fopen("./out_gold.dat","r");
        for(m=0;m<Data_Num;m=m+1) begin
            input_data = $fscanf(Din,"%d", Din_list[m]);
            golden_data = $fscanf(golden,"%d", golden_list[m]);
            data_length = data_length + 1;
        end
    end

    integer i;
    initial begin
        $display("------------Start simulation-----------");
        wait (axis_rst_n);
        ss_tvalid = 0;
        $display("----Start the data input(AXI-Stream)----");
        for(i=0;i<(data_length-1);i=i+1) begin
            ss_tlast = 0; ss(Din_list[i]);
        end
        config_read_check(12'h00, 32'h00, 32'h0000_000f); // check idle = 0
        ss_tlast = 1; ss(Din_list[(Data_Num-1)]);
        $display("------End the data input(AXI-Stream)------");
    end

    integer k;
    reg error;
    reg status_error;
    reg error_coef;
    initial begin
        error = 0; status_error = 0;
        sm_tready = 1;
        wait (sm_tvalid);
        for(k=0;k < data_length;k=k+1) begin
            sm(golden_list[k],k);
        end
        config_read_check(12'h00, 32'h02, 32'h0000_0002); // check ap_done = 1 (0x00 [bit 1])
        clk_done = 1;
        config_read_check(12'h00, 32'h04, 32'h0000_0004); // check ap_idle = 1 (0x00 [bit 2])
        if (error == 0 & error_coef == 0) begin
            $display("---------------------------------------------");
            $display("-----------Congratulations! Pass-------------");
        end
        else begin
            $display("--------Simulation Failed---------");
        end
        $finish;
    end

    // Prevent hang
    integer timeout = (1000000);
    initial begin
        while(timeout > 0) begin
            @(posedge axis_clk);
            timeout = timeout - 1;
        end
        $display($time, "Simualtion Hang ....");
        $finish;
    end


    reg signed [31:0] coef[0:10]; // fill in coef 
    initial begin
        coef[0]  =  32'd0;
        coef[1]  = -32'd10;
        coef[2]  = -32'd9;
        coef[3]  =  32'd23;
        coef[4]  =  32'd56;
        coef[5]  =  32'd63;
        coef[6]  =  32'd56;
        coef[7]  =  32'd23;
        coef[8]  = -32'd9;
        coef[9]  = -32'd10;
        coef[10] =  32'd0;
    end

//    reg error_coef;
    initial begin
        error_coef = 0;
        $display("----Start the coefficient input(AXI-lite)----");
        config_write(12'h10, data_length);
        for(k=0; k< Tape_Num; k=k+1) begin
            config_write(12'h80+4*k, coef[k]);
        end
        awvalid <= 0; wvalid <= 0;
        // read-back and check
        $display(" Check Coefficient ...");
        for(k=0; k < Tape_Num; k=k+1) begin
            config_read_check(12'h80+4*k, coef[k], 32'hffffffff);
        end
        arvalid <= 0;
        $display(" Tape programming done ...");
        $display(" Start FIR");
        @(posedge axis_clk) config_write(12'h00, 32'h0000_0001);    // ap_start = 1
        clk_start = 1;
        awvalid <= 0; wvalid <= 0;
        $display("----End the coefficient input(AXI-lite)----");
    end

    task config_write;
        input [11:0]    addr;
        input [31:0]    data;
        begin
            awvalid <= 0; wvalid <= 0;
            @(posedge axis_clk);
            awvalid <= 1; awaddr <= addr;
            wvalid  <= 1; wdata <= data;
            @(posedge axis_clk);
            while (!wready) @(posedge axis_clk);
        end
    endtask

    task config_read_check;
        input [11:0]        addr;
        input signed [31:0] exp_data;
        input [31:0]        mask;
        begin
            arvalid <= 0;
            @(posedge axis_clk);
            arvalid <= 1; araddr <= addr;
            rready <= 1;
            @(posedge axis_clk);
            while (!rvalid) @(posedge axis_clk);
            if( (rdata & mask) != (exp_data & mask)) begin
                $display("ERROR: exp = %d, rdata = %d", exp_data, rdata);
                error_coef <= 1;
            end else begin
                $display("OK: exp = %d, rdata = %d", exp_data, rdata);
            end
        end
    endtask



    task ss;
        input  signed [31:0] in1;
        begin
            ss_tvalid <= 1;
            ss_tdata  <= in1;
            @(posedge axis_clk);
            while (!ss_tready) begin
                @(posedge axis_clk);
            end
        end
    endtask

    task sm;
        input  signed [31:0] in2; // golden data
        input         [31:0] pcnt; // pattern count
        begin
            sm_tready <= 1;
            @(posedge axis_clk) 
            wait(sm_tvalid);
            while(!sm_tvalid) @(posedge axis_clk);
            if (sm_tdata != in2) begin
                $display("[ERROR] [Pattern %d] Golden answer: %d, Your answer: %d", pcnt, in2, sm_tdata);
                error <= 1;
            end
            else begin
                $display("[PASS] [Pattern %d] Golden answer: %d, Your answer: %d", pcnt, in2, sm_tdata);
            end
            @(posedge axis_clk);
        end
    endtask
endmodule

Lab3/waveform/fir.vcd
$date
    Oct 22, 2023  15:48:33
$end
$version
    TOOL:	ncsim(64)	15.20-s084
$end
$timescale
    1 ps
$end

$scope module fir_tb $end
$var parameter 32 !    pADDR_WIDTH  $end
$var parameter 32 "    pDATA_WIDTH  $end
$var parameter 32 #    Tape_Num  $end
$var parameter 32 $    Data_Num  $end
$var wire      1 %    awready  $end
$var wire      1 &    wready  $end
$var reg       1 '    awvalid  $end
$var reg      12 (    awaddr [11:0] $end
$var reg       1 )    wvalid  $end
$var reg      32 *    wdata [31:0] $end
$var wire      1 +    arready  $end
$var reg       1 ,    rready  $end
$var reg       1 -    arvalid  $end
$var reg      12 .    araddr [11:0] $end
$var wire      1 /    rvalid  $end
$var wire     32 0    rdata [31:0] $end
$var reg       1 1    ss_tvalid  $end
$var reg      32 2    ss_tdata [31:0] $end
$var reg       1 3    ss_tlast  $end
$var wire      1 4    ss_tready  $end
$var reg       1 5    sm_tready  $end
$var wire      1 6    sm_tvalid  $end
$var wire     32 7    sm_tdata [31:0] $end
$var wire      1 8    sm_tlast  $end
$var reg       1 9    axis_clk  $end
$var reg       1 :    axis_rst_n  $end
$var wire      4 ;    tap_WE [3:0] $end
$var wire      1 <    tap_EN  $end
$var wire     32 =    tap_Di [31:0] $end
$var wire     12 >    tap_A [11:0] $end
$var wire     32 ?    tap_Do [31:0] $end
$var wire      4 @    data_WE [3:0] $end
$var wire      1 A    data_EN  $end
$var wire     32 B    data_Di [31:0] $end
$var wire     12 C    data_A [11:0] $end
$var wire     32 D    data_Do [31:0] $end
$var integer  32 E    clk_start  $end
$var integer  32 F    clk_done  $end
$var integer  32 G    clk_accu  $end
$var reg      32 H    data_length [31:0] $end
$var integer  32 I    Din  $end
$var integer  32 J    golden  $end
$var integer  32 K    input_data  $end
$var integer  32 L    golden_data  $end
$var integer  32 M    m  $end
$var integer  32 N    i  $end
$var integer  32 O    k  $end
$var reg       1 P    error  $end
$var reg       1 Q    status_error  $end
$var reg       1 R    error_coef  $end
$var integer  32 S    timeout  $end

$scope module fir_DUT $end
$var parameter 32 T    pADDR_WIDTH  $end
$var parameter 32 U    pDATA_WIDTH  $end
$var parameter 32 V    Tape_Num  $end
$var wire      1 %    awready  $end
$var wire      1 &    wready  $end
$var wire      1 W    awvalid  $end
$var wire     12 X    awaddr [11:0] $end
$var wire      1 Y    wvalid  $end
$var wire     32 Z    wdata [31:0] $end
$var wire      1 +    arready  $end
$var wire      1 [    rready  $end
$var wire      1 \    arvalid  $end
$var wire     12 ]    araddr [11:0] $end
$var wire      1 /    rvalid  $end
$var wire     32 0    rdata [31:0] $end
$var wire      1 ^    ss_tvalid  $end
$var wire     32 _    ss_tdata [31:0] $end
$var wire      1 `    ss_tlast  $end
$var wire      1 4    ss_tready  $end
$var wire      1 a    sm_tready  $end
$var wire      1 6    sm_tvalid  $end
$var wire     32 7    sm_tdata [31:0] $end
$var wire      1 8    sm_tlast  $end
$var wire      4 ;    tap_WE [3:0] $end
$var wire      1 <    tap_EN  $end
$var wire     32 =    tap_Di [31:0] $end
$var wire     12 >    tap_A [11:0] $end
$var wire     32 ?    tap_Do [31:0] $end
$var wire      4 @    data_WE [3:0] $end
$var wire      1 A    data_EN  $end
$var wire     32 B    data_Di [31:0] $end
$var wire     12 C    data_A [11:0] $end
$var wire     32 D    data_Do [31:0] $end
$var wire      1 b    axis_clk  $end
$var wire      1 c    axis_rst_n  $end
$var reg       1 d    r_awready  $end
$var reg       1 e    r_wready  $end
$var reg       1 f    r_arready  $end
$var reg       1 g    r_rvalid  $end
$var reg       1 h    r_ss_tready  $end
$var reg       1 i    r_sm_tvalid  $end
$var reg       1 j    r_sm_tlast  $end
$var reg      32 k    r_rdata [31:0] $end
$var reg      32 l    r_sm_tdata [31:0] $end
$var reg       1 m    out_awready  $end
$var reg       1 n    out_wready  $end
$var reg       1 o    out_arready  $end
$var reg       1 p    out_rvalid  $end
$var reg       1 q    out_ss_tready  $end
$var reg       1 r    out_sm_tvalid  $end
$var reg       1 s    out_sm_tlast  $end
$var reg      32 t    out_rdata [31:0] $end
$var reg      32 u    out_sm_tdata [31:0] $end
$var reg       1 v    m_tap_EN  $end
$var reg       1 w    m_data_EN  $end
$var reg       4 x    m_tap_WE [3:0] $end
$var reg       4 y    m_data_WE [3:0] $end
$var reg      32 z    m_tap_Di [31:0] $end
$var reg      32 {    m_data_Di [31:0] $end
$var reg      12 |    m_tap_A [11:0] $end
$var reg      12 }    m_data_A [11:0] $end
$var reg       1 ~    ap_start  $end
$var reg       1 !!   n_ap_start  $end
$var reg       1 "!   ap_done  $end
$var reg       1 #!   n_ap_done  $end
$var reg       1 $!   ap_idle  $end
$var reg       1 %!   n_ap_idle  $end
$var reg       1 &!   out_rvalid_pre  $end
$var reg       1 '!   out_rvalid_reg  $end
$var reg       1 (!   last_flag  $end
$var reg       1 )!   n_last_flag  $end
$var reg      11 *!   data_num [10:0] $end
$var reg      11 +!   n_data_num [10:0] $end
$var reg      32 ,!   y [31:0] $end
$var reg      32 -!   pre_y [31:0] $end
$var reg      32 .!   n_y [31:0] $end
$var reg       4 /!   count_a [3:0] $end
$var reg       4 0!   count_x [3:0] $end
$var reg       4 1!   count [3:0] $end
$var reg       4 2!   addr_flag [3:0] $end
$var reg       4 3!   n_addr_flag [3:0] $end
$var reg       5 4!   sum [4:0] $end
$var reg       2 5!   state [1:0] $end
$var reg       2 6!   n_state [1:0] $end
$var parameter  2 7!   IDLE  $end
$var parameter  2 8!   COEF  $end
$var parameter  2 9!   FIRR  $end
$var parameter  2 :!   IDLE2  $end
$upscope $end


$scope module tap_RAM $end
$var wire      1 b    CLK  $end
$var wire      4 ;    WE [3:0] $end
$var wire      1 <    EN  $end
$var wire     32 =    Di [31:0] $end
$var reg      32 ;!   Do [31:0] $end
$var wire     12 >    A [11:0] $end
$var reg      12 <!   r_A [11:0] $end
$var reg      32 =!   Temp_D [31:0] $end
$upscope $end


$scope module data_RAM $end
$var wire      1 b    CLK  $end
$var wire      4 @    WE [3:0] $end
$var wire      1 A    EN  $end
$var wire     32 B    Di [31:0] $end
$var reg      32 >!   Do [31:0] $end
$var wire     12 C    A [11:0] $end
$var reg      12 ?!   r_A [11:0] $end
$var reg      32 @!   Temp_D [31:0] $end
$upscope $end


$scope task config_write $end
$var reg      12 A!   addr [11:0] $end
$var reg      32 B!   data [31:0] $end
$upscope $end


$scope task config_read_check $end
$var reg      12 C!   addr [11:0] $end
$var reg      32 D!   exp_data [31:0] $end
$var reg      32 E!   mask [31:0] $end
$upscope $end


$scope task ss $end
$var reg      32 F!   in1 [31:0] $end
$upscope $end


$scope task sm $end
$var reg      32 G!   in2 [31:0] $end
$var reg      32 H!   pcnt [31:0] $end
$upscope $end

$upscope $end

$enddefinitions $end
$dumpvars
b11 :!
b10 9!
b1 8!
b0 7!
b1011 V
b100000 U
b1100 T
b1001011000 $
b1011 #
b100000 "
b1100 !
x%
x&
0'
bx (
0)
bx *
x+
x,
x-
bx .
x/
bx 0
x1
bx 2
x3
x4
15
x6
bx 7
x8
09
0:
b0 ;
0<
b0 =
b0 >
b0 ?
bx @
xA
bx B
b0xxxxx00 C
bx D
b0 E
b0 F
b0 G
b1001011000 H
b10000000000000000000000000000011 I
b10000000000000000000000000000100 J
b1 K
b1 L
b1001011000 M
bx N
bx O
0P
0Q
0R
b11110100001001000000 S
0W
bx X
0Y
bx Z
x[
x\
bx ]
x^
bx _
x`
1a
0b
0c
xd
xe
xf
xg
xh
xi
xj
bx k
bx l
xm
xn
xo
0p
xq
xr
xs
b0 t
bx u
0v
xw
b0 x
bx y
b0 z
bx {
b0 |
b0xxxxx00 }
x~
x!!
x"!
x#!
x$!
x%!
0&!
x'!
x(!
x)!
bx *!
bx +!
bx ,!
bx -!
bx .!
bx /!
bx 0!
bx 1!
bx 2!
bx 3!
bx 4!
bx 5!
bx 6!
b0 ;!
bx <!
bx =!
bx >!
bx ?!
bx @!
b10000 A!
b1001011000 B!
bx C!
bx D!
bx E!
bx F!
bx G!
bx H!
$end
#5000
19
b11110100001000111111 S
1b
1'
b10000 (
1)
b1001011000 *
b0xxxxx00 ?!
b0 <!
b0 5!
0~
0"!
1$!
b0 *!
0d
0e
0f
0g
0h
0i
0j
b0 k
b0 l
0'!
0(!
b0 -!
b0 /!
b0 0!
b1 2!
1%!
b1 6!
b1 4!
b0 y
b100 }
0w
b0 1!
b0 .!
0!!
0#!
b0 +!
0q
0r
0s
1o
1m
1n
b1 3!
0A
b100 C
b0 @
b0 7
b0 0
08
06
04
0/
0+
0&
0%
b1001011000 Z
1Y
b10000 X
1W
b0 >!
b1001011000 +!
b0 D
b0 ,!
b0 u
#10000
09
0b
#15000
19
1:
b11110100001000111110 S
01
b0 N
03
b1 F!
0`
0^
1c
1b
0)!
11
b1 2
b100 ?!
b1 5!
b1001011000 *!
1d
1e
1f
b0 }
b0 {
b0 B
b0 C
1+
1&
1%
b1 _
1^
#20000
09
0b
#25000
19
b11110100001000111101 S
b0 O
b10000000 A!
b0 B!
1b
0'
0)
b0 ?!
0Y
0W
#30000
09
0b
#35000
19
b11110100001000111100 S
1b
1'
b10000000 (
1)
b0 *
b0 Z
1Y
b10000000 X
1W
1v
b1111 x
b1111 y
1w
1A
b1111 @
b1111 ;
1<
bx >!
bx ;!
bx ?
bx D
bx ,!
bx u
#40000
09
0b
#45000
19
b11110100001000111011 S
b1 O
b10000100 A!
b11111111111111111111111111110110 B!
1b
0'
0)
bx l
b0 >!
b0 ;!
b0 ?
b0 D
bx 7
0Y
0W
b0 ,!
0v
b0 x
b0 u
b0 y
0w
0A
b0 @
b0 ;
0<
#50000
09
0b
#55000
19
b11110100001000111010 S
1b
1'
b10000100 (
1)
b11111111111111111111111111110110 *
b0 l
b0 7
b11111111111111111111111111110110 Z
1Y
b10000100 X
1W
b100 |
1v
b1111 x
b11111111111111111111111111110110 z
b1111 y
b100 }
1w
1A
b100 C
b1111 @
b11111111111111111111111111110110 =
b1111 ;
1<
b100 >
#60000
09
0b
#65000
19
b11110100001000111001 S
b10 O
b10001000 A!
b11111111111111111111111111110111 B!
1b
0'
0)
b100 ?!
b100 <!
b11111111111111111111111111110110 ;!
b11111111111111111111111111110110 ?
0Y
0W
b0 |
0v
b0 x
b0 z
b0 y
b0 }
0w
0A
b0 C
b0 @
b0 =
b0 ;
0<
b0 >
b0 ;!
b0 ?
#70000
09
0b
#75000
19
b11110100001000111000 S
1b
1'
b10001000 (
1)
b11111111111111111111111111110111 *
b0 ?!
b0 <!
b11111111111111111111111111110111 Z
1Y
b10001000 X
1W
b1000 |
1v
b1111 x
b11111111111111111111111111110111 z
b1111 y
b1000 }
1w
1A
b1000 C
b1111 @
b11111111111111111111111111110111 =
b1111 ;
1<
b1000 >
#80000
09
0b
#85000
19
b11110100001000110111 S
b11 O
b10001100 A!
b10111 B!
1b
0'
0)
b1000 ?!
b1000 <!
b11111111111111111111111111110111 ;!
b11111111111111111111111111110111 ?
0Y
0W
b0 |
0v
b0 x
b0 z
b0 y
b0 }
0w
0A
b0 C
b0 @
b0 =
b0 ;
0<
b0 >
b0 ;!
b0 ?
#90000
09
0b
#95000
19
b11110100001000110110 S
1b
1'
b10001100 (
1)
b10111 *
b0 ?!
b0 <!
b10111 Z
1Y
b10001100 X
1W
b1100 |
1v
b1111 x
b10111 z
b1111 y
b1100 }
1w
1A
b1100 C
b1111 @
b10111 =
b1111 ;
1<
b1100 >
#100000
09
0b
#105000
19
b11110100001000110101 S
b100 O
b10010000 A!
b111000 B!
1b
0'
0)
b1100 ?!
b1100 <!
b10111 ;!
b10111 ?
0Y
0W
b0 |
0v
b0 x
b0 z
b0 y
b0 }
0w
0A
b0 C
b0 @
b0 =
b0 ;
0<
b0 >
b0 ;!
b0 ?
#110000
09
0b
#115000
19
b11110100001000110100 S
1b
1'
b10010000 (
1)
b111000 *
b0 ?!
b0 <!
b111000 Z
1Y
b10010000 X
1W
b10000 |
1v
b1111 x
b111000 z
b1111 y
b10000 }
1w
1A
b10000 C
b1111 @
b111000 =
b1111 ;
1<
b10000 >
#120000
09
0b
